ws_import_spdx/__init__.py
ws_import_spdx/_version.py
ws_import_spdx/conftest.py
ws_import_spdx/import_const.py
ws_import_spdx/import_spdx.py
ws_import_spdx-22.12.3.1.dist-info/LICENSE
ws_import_spdx-22.12.3.1.dist-info/METADATA
ws_import_spdx-22.12.3.1.dist-info/WHEEL
ws_import_spdx-22.12.3.1.dist-info/entry_points.txt
ws_import_spdx-22.12.3.1.dist-info/top_level.txt
ws_import_spdx-22.12.3.1.dist-info/RECORD
