Metadata-Version: 2.1
Name: ws-import-spdx
Version: 22.12.3.1
Summary: Preparation upload file for Mend UI
Home-page: https://github.com/whitesource-ps/ws-import-spdx
Author: WhiteSource Professional Services
Author-email: ps@whitesourcesoftware.com
License: LICENSE.txt
Classifier: Programming Language :: Python :: 3.8
Classifier: Programming Language :: Python :: 3.9
Classifier: Programming Language :: Python :: 3.10
Classifier: License :: OSI Approved :: Apache Software License
Classifier: Operating System :: OS Independent
Requires-Python: >=3.8
License-File: LICENSE
